ovos_tts_plugin_mimic3/__init__.py
ovos_tts_plugin_mimic3/version.py
ovos_tts_plugin_mimic3-0.0.0.dist-info/LICENSE
ovos_tts_plugin_mimic3-0.0.0.dist-info/METADATA
ovos_tts_plugin_mimic3-0.0.0.dist-info/WHEEL
ovos_tts_plugin_mimic3-0.0.0.dist-info/entry_points.txt
ovos_tts_plugin_mimic3-0.0.0.dist-info/top_level.txt
ovos_tts_plugin_mimic3-0.0.0.dist-info/RECORD
